simplemonitor/Alerters/__init__.py
simplemonitor/Alerters/alerter.py
simplemonitor/Alerters/bulksms.py
simplemonitor/Alerters/execute.py
simplemonitor/Alerters/fortysixelks.py
simplemonitor/Alerters/healthchecks.py
simplemonitor/Alerters/mail.py
simplemonitor/Alerters/nc.py
simplemonitor/Alerters/nextcloud_notification.py
simplemonitor/Alerters/ntfy.py
simplemonitor/Alerters/pushbullet.py
simplemonitor/Alerters/pushover.py
simplemonitor/Alerters/ses.py
simplemonitor/Alerters/slack.py
simplemonitor/Alerters/sms77.py
simplemonitor/Alerters/sns.py
simplemonitor/Alerters/syslogger.py
simplemonitor/Alerters/telegram.py
simplemonitor/Alerters/twilio.py
simplemonitor/Loggers/__init__.py
simplemonitor/Loggers/db.py
simplemonitor/Loggers/file.py
simplemonitor/Loggers/logger.py
simplemonitor/Loggers/mqtt.py
simplemonitor/Loggers/network.py
simplemonitor/Loggers/seq.py
simplemonitor/Monitors/__init__.py
simplemonitor/Monitors/arlo.py
simplemonitor/Monitors/compound.py
simplemonitor/Monitors/file.py
simplemonitor/Monitors/gmirror.py
simplemonitor/Monitors/hass.py
simplemonitor/Monitors/host.py
simplemonitor/Monitors/monitor.py
simplemonitor/Monitors/network.py
simplemonitor/Monitors/ring.py
simplemonitor/Monitors/service.py
simplemonitor/Monitors/unifi.py
simplemonitor/__init__.py
simplemonitor/const.py
simplemonitor/html/dist/2b3e1faf89f94a483539.png
simplemonitor/html/dist/416d91365b44e4b4f477.png
simplemonitor/html/dist/6733b337e5bc285232c2.png
simplemonitor/html/dist/8f2c4d11474275fbc161.png
simplemonitor/html/dist/a47ad8a0da980112e2cd.png
simplemonitor/html/dist/fc32c7cbd6407867571b.png
simplemonitor/html/dist/main.bundle.js
simplemonitor/html/dist/main.bundle.js.LICENSE.txt
simplemonitor/html/dist/maps.bundle.js
simplemonitor/html/dist/maps.bundle.js.LICENSE.txt
simplemonitor/html/package-lock.json
simplemonitor/html/package.json
simplemonitor/html/src/index.js
simplemonitor/html/src/maps.js
simplemonitor/html/src/marker-shadow.png
simplemonitor-1.15.0.dist-info/METADATA
simplemonitor-1.15.0.dist-info/WHEEL
simplemonitor-1.15.0.dist-info/entry_points.txt
simplemonitor-1.15.0.dist-info/licenses/LICENCE
simplemonitor-1.15.0.dist-info/RECORD
