Metadata-Version: 2.4
Name: simplemonitor
Version: 1.15.0
Summary: A simple network and host monitor
License-Expression: BSD-3-Clause
License-File: LICENCE
Author: James Seward
Author-email: james@jamesoff.net
Requires-Python: >=3.10
Classifier: Development Status :: 5 - Production/Stable
Classifier: Environment :: Console
Classifier: Environment :: No Input/Output (Daemon)
Classifier: Intended Audience :: System Administrators
Classifier: License :: OSI Approved :: BSD License
Classifier: Operating System :: OS Independent
Classifier: Programming Language :: Python :: 3 :: Only
Classifier: Programming Language :: Python :: 3
Classifier: Topic :: System :: Monitoring
Classifier: Typing :: Typed
Requires-Dist: Jinja2 (>=2.11.2,<4.0.0)
Requires-Dist: arrow (>=0.17,<1.4)
Requires-Dist: boto3 (>=1.15.16,<2.0.0)
Requires-Dist: colorlog (>=4.4)
Requires-Dist: icmplib (>=3.0.3,<4.0.0)
Requires-Dist: paho-mqtt (>=1.5.1,<2.0.0)
Requires-Dist: paramiko (>=2.7.2,<4.0.0)
Requires-Dist: psutil (>=5.7.2,<8.0.0)
Requires-Dist: pyaarlo (>=0.7.1.3,<0.9.0.0)
Requires-Dist: pync (>=2.0.3,<3.0.0) ; sys_platform == "darwin"
Requires-Dist: pywin32 (>=228,<312) ; sys_platform == "win32"
Requires-Dist: requests (>=2.32.5,<3.0.0)
Requires-Dist: ring-doorbell (>=0.6.0)
Requires-Dist: twilio (>=7.16.4,<8.0.0)
Project-URL: Documentation, http://jamesoff.github.io/simplemonitor/
Project-URL: Homepage, https://github.com/jamesoff/simplemonitor
Project-URL: Repository, https://github.com/jamesoff/simplemonitor
